{
    "table": {
        "name": "commands",
        "__meta__": "cogs.stats.Commands",
        "columns": [
            {
                "column_type": {
                    "big": false,
                    "small": false,
                    "auto_increment": true,
                    "__meta__": "cogs.utils.db.Integer"
                },
                "index": false,
                "primary_key": true,
                "nullable": true,
                "default": null,
                "unique": false,
                "name": "id",
                "index_name": null
            },
            {
                "column_type": {
                    "big": true,
                    "small": false,
                    "auto_increment": false,
                    "__meta__": "cogs.utils.db.Integer"
                },
                "index": true,
                "primary_key": false,
                "nullable": true,
                "default": null,
                "unique": false,
                "name": "guild_id",
                "index_name": "commands_guild_id_idx"
            },
            {
                "column_type": {
                    "big": true,
                    "small": false,
                    "auto_increment": false,
                    "__meta__": "cogs.utils.db.Integer"
                },
                "index": false,
                "primary_key": false,
                "nullable": true,
                "default": null,
                "unique": false,
                "name": "channel_id",
                "index_name": null
            },
            {
                "column_type": {
                    "big": true,
                    "small": false,
                    "auto_increment": false,
                    "__meta__": "cogs.utils.db.Integer"
                },
                "index": true,
                "primary_key": false,
                "nullable": true,
                "default": null,
                "unique": false,
                "name": "author_id",
                "index_name": "commands_author_id_idx"
            },
            {
                "column_type": {
                    "timezone": false,
                    "__meta__": "cogs.utils.db.Datetime"
                },
                "index": true,
                "primary_key": false,
                "nullable": true,
                "default": null,
                "unique": false,
                "name": "used",
                "index_name": "commands_used_idx"
            },
            {
                "column_type": {
                    "length": null,
                    "fixed": false,
                    "__meta__": "cogs.utils.db.String"
                },
                "index": false,
                "primary_key": false,
                "nullable": true,
                "default": null,
                "unique": false,
                "name": "prefix",
                "index_name": null
            },
            {
                "column_type": {
                    "length": null,
                    "fixed": false,
                    "__meta__": "cogs.utils.db.String"
                },
                "index": true,
                "primary_key": false,
                "nullable": true,
                "default": null,
                "unique": false,
                "name": "command",
                "index_name": "commands_command_idx"
            },
            {
                "column_type": {
                    "__meta__": "cogs.utils.db.Boolean"
                },
                "index": true,
                "primary_key": false,
                "nullable": true,
                "default": null,
                "unique": false,
                "name": "failed",
                "index_name": "commands_failed_idx"
            }
        ]
    },
    "migrations": []
}